{
  "Name": "Martin Helstáb",
  "DisplayName": null,
  "MediaContact": "www.instagram.com/bighelstab",
  "DateOfBirth": {
    "Year": 1995,
    "Month": 3,
    "Day": 23
  },
  "Biomarkers": [
    {
      "Date": "2025-07-17",
      "AlbGL": 51.7,
      "CreatUmolL": 77.1,
      "GluMmolL": 5.62,
      "CrpMgL": 0.2,
      "LymPc": 33.4,
      "McvFL": 89.8,
      "RdwPc": 10.2,
      "AlpUL": 109,
      "Wbc1000cellsuL": 5.79
    },
    {
      "Date": "2025-10-31",
      "AlbGL": 50,
      "CreatUmolL": 68,
      "GluMmolL": 4.7,
      "CrpMgL": 0.98,
      "LymPc": 31,
      "McvFL": 89,
      "RdwPc": 11.3,
      "AlpUL": 80,
      "Wbc1000cellsuL": 5.5
    },
    {
      "Date": "2026-02-28",
      "AlbGL": 48,
      "CreatUmolL": 88,
      "GluMmolL": 4,
      "CrpMgL": 0.5,
      "LymPc": 33.6,
      "McvFL": 89,
      "RdwPc": 11.7,
      "AlpUL": 73,
      "Wbc1000cellsuL": 5.2,
      "NeutrophilPc": 58.6,
      "MonocytePc": 6.8,
      "Rbc10e12L": 5,
      "MchPg": 30,
      "UreaMmolL": 4.5,
      "CystatinCMgL": 0.64,
      "Hba1cMmolMol": 32,
      "CholesterolMmolL": 4.4,
      "ApoA1GL": 1.44,
      "AltUL": 14,
      "GgtUL": 18,
      "ShbgNmolL": 73,
      "VitaminDNmolL": 235
    },
    {
      "Date": "2026-05-30",
      "AlbGL": 48,
      "CreatUmolL": 98,
      "GluMmolL": 4.6,
      "CrpMgL": 0.26,
      "LymPc": 28.5,
      "McvFL": 92,
      "RdwPc": 11.6,
      "AlpUL": 69,
      "Wbc1000cellsuL": 7.1,
      "NeutrophilPc": 60.8,
      "MonocytePc": 9,
      "Rbc10e12L": 5.3,
      "MchPg": 30,
      "UreaMmolL": 6.1,
      "CystatinCMgL": 0.62,
      "Hba1cMmolMol": 24,
      "CholesterolMmolL": 4.5,
      "ApoA1GL": 1.49,
      "AltUL": 16,
      "GgtUL": 11,
      "ShbgNmolL": 21.8,
      "VitaminDNmolL": 205
    }
  ],
  "Division": "Men's",
  "Flag": "Hungary",
  "Why": "As a transhumanist artist and thinker, I pursue unlimited life extension, firstly through biohacking.",
  "PersonalLink": "https://www.instagram.com/bighelstab"
}
